promptflow_tool_semantic_kernel/.tool_meta_cache.yaml
promptflow_tool_semantic_kernel/__init__.py
promptflow_tool_semantic_kernel/tools/__init__.py
promptflow_tool_semantic_kernel/tools/chat_history_processor.py
promptflow_tool_semantic_kernel/tools/kernel_factory.py
promptflow_tool_semantic_kernel/tools/lights_plugin.py
promptflow_tool_semantic_kernel/tools/logger_factory.py
promptflow_tool_semantic_kernel/tools/plugin_manager.py
promptflow_tool_semantic_kernel/tools/response_processor.py
promptflow_tool_semantic_kernel/tools/response_strategy.py
promptflow_tool_semantic_kernel/tools/semantic_kernel_tool.py
promptflow_tool_semantic_kernel/tools/tracing_disabler.py
promptflow_tool_semantic_kernel/tools/utils.py
promptflow_tool_semantic_kernel/yamls/__init__.py
promptflow_tool_semantic_kernel/yamls/semantic_kernel_tool.yaml
promptflow_tool_semantic_kernel-0.2.3.dist-info/LICENSE
promptflow_tool_semantic_kernel-0.2.3.dist-info/METADATA
promptflow_tool_semantic_kernel-0.2.3.dist-info/WHEEL
promptflow_tool_semantic_kernel-0.2.3.dist-info/entry_points.txt
promptflow_tool_semantic_kernel-0.2.3.dist-info/RECORD
