Metadata-Version: 2.3
Name: promptflow-tool-semantic-kernel
Version: 0.2.3
Summary: 
License: AGPL-3.0-only
Author: Fabian Schurig
Author-email: fabian.a.schurig@gmail.com
Requires-Python: >=3.10,<3.13
Classifier: License :: OSI Approved :: GNU Affero General Public License v3
Classifier: Programming Language :: Python :: 3
Classifier: Programming Language :: Python :: 3.10
Classifier: Programming Language :: Python :: 3.11
Classifier: Programming Language :: Python :: 3.12
Requires-Dist: fastapi (>=0.115.10,<0.116.0)
Requires-Dist: google-generativeai (>=0.8.4,<0.9.0)
Requires-Dist: keyrings-alt (>=5.0.2,<6.0.0)
Requires-Dist: promptflow (>=1.17.2,<2.0.0)
Requires-Dist: promptflow-tracing (>=1.17.2,<2.0.0)
Requires-Dist: semantic-kernel (>=1.22.0,<2.0.0)
Requires-Dist: uvicorn (>=0.34.0,<0.35.0)
